test/__init__.py
test/general_tools.py
utility_toolkit/__init__.py
utility_toolkit/aws_tools.py
utility_toolkit/dynamodb_handler.py
utility_toolkit/general_tools.py
utility_toolkit/log.py
utility_toolkit/postgresql_handler.py
utility_toolkit/sqlite_handler.py
utility_toolkit/sqs_handler.py
utility_toolkit-0.2.3.dist-info/METADATA
utility_toolkit-0.2.3.dist-info/WHEEL
utility_toolkit-0.2.3.dist-info/top_level.txt
utility_toolkit-0.2.3.dist-info/RECORD
