Metadata-Version: 2.4
Name: utility_toolkit
Version: 0.2.3
Summary: A comprehensive toolkit for AWS operations, database handling, and general utilities.
Author-email: Eslam Hasanen <Eslamspot@gmail.com>
Project-URL: Homepage, https://www.idealisticsolutions.com
Project-URL: Bug Tracker, https://github.com/eslamspot/utility_toolkit/issues
Keywords: tools_box,tools,utilities,toolkit
Classifier: License :: OSI Approved :: MIT License
Classifier: Programming Language :: Python
Classifier: Programming Language :: Python :: 3
Classifier: Programming Language :: Python :: 3.8
Classifier: Programming Language :: Python :: 3.9
Classifier: Programming Language :: Python :: 3.10
Classifier: Programming Language :: Python :: 3.11
Classifier: Programming Language :: Python :: 3.12
Requires-Python: >=3.8
Requires-Dist: beautifulsoup4
Requires-Dist: boto3
Requires-Dist: botocore
Requires-Dist: chardet==5.2.0
Requires-Dist: cryptography==44.0.0
Requires-Dist: lxml==5.3.0
Requires-Dist: pdfkit==1.0.0
Requires-Dist: Pillow
Requires-Dist: psutil==6.1.0
Requires-Dist: reportlab==4.2.5
Requires-Dist: Requests
Requires-Dist: tqdm
Provides-Extra: dev
Requires-Dist: pytest; extra == "dev"
Requires-Dist: black; extra == "dev"
Requires-Dist: flake8; extra == "dev"
Requires-Dist: toolkit; extra == "dev"
Requires-Dist: tools_box; extra == "dev"
Requires-Dist: tools; extra == "dev"
Requires-Dist: utilities; extra == "dev"
